pytonlib_telemint/__init__.py
pytonlib_telemint/telemint.py
pytonlib_telemint-0.0.1.dist-info/LICENSE
pytonlib_telemint-0.0.1.dist-info/METADATA
pytonlib_telemint-0.0.1.dist-info/WHEEL
pytonlib_telemint-0.0.1.dist-info/top_level.txt
pytonlib_telemint-0.0.1.dist-info/RECORD
