Metadata-Version: 2.1
Name: pytonlib-telemint
Version: 0.0.1
Summary: PyTONLib utility for Telemint NFTs
Home-page: https://github.com/Natanel-Shitrit/pytonlib-telemint
Author: Natanel Shitrit
Author-email: natanelsht@gmail.com
Project-URL: Bug Tracker, https://github.com/Natanel-Shitrit/pytonlib-telemint/issues
Classifier: Programming Language :: Python :: 3
Classifier: License :: OSI Approved :: GNU General Public License v3 (GPLv3)
Classifier: Operating System :: OS Independent
License-File: LICENSE
Requires-Dist: pytonlib
